allegro/__init__.py
allegro/_compile.py
allegro/_extern.py
allegro/_version.py
allegro/model/__init__.py
allegro/model/allegro_models.py
allegro/nn/__init__.py
allegro/nn/_allegro.py
allegro/nn/_edgeembed.py
allegro/nn/edgewise.py
allegro/nn/scalarembed.py
allegro/nn/spline.py
allegro/nn/tensorembed.py
allegro/nn/_strided/__init__.py
allegro/nn/_strided/_channels.py
allegro/nn/_strided/_contract.py
allegro/nn/_strided/_cueq_contracter.py
allegro/nn/_strided/_flashallegro.py
allegro/nn/_strided/_lexsort.py
nequip_allegro-0.8.1.dist-info/licenses/LICENSE
nequip_allegro-0.8.1.dist-info/METADATA
nequip_allegro-0.8.1.dist-info/WHEEL
nequip_allegro-0.8.1.dist-info/entry_points.txt
nequip_allegro-0.8.1.dist-info/top_level.txt
nequip_allegro-0.8.1.dist-info/RECORD
