Metadata-Version: 2.4
Name: nequip-allegro
Version: 0.8.1
Summary: Allegro is an open-source code for building highly scalable and accurate equivariant deep learning interatomic potentials.
Author-email: The NequIP Developers <allegro-nequip@g.harvard.edu>
License: MIT License
Project-URL: Repository, https://github.com/mir-group/allegro
Requires-Python: >=3.10
License-File: LICENSE
Requires-Dist: nequip>=0.16.0
Dynamic: license-file
